fast_bitrix24_mcp/__init__.py
fast_bitrix24_mcp/main.py
fast_bitrix24_mcp/promts/__init__.py
fast_bitrix24_mcp/promts/promts.py
fast_bitrix24_mcp/resources/__init__.py
fast_bitrix24_mcp/resources/userfields.py
fast_bitrix24_mcp/tools/__init__.py
fast_bitrix24_mcp/tools/activity_decline.py
fast_bitrix24_mcp/tools/bitrixWork.py
fast_bitrix24_mcp/tools/company.py
fast_bitrix24_mcp/tools/contact.py
fast_bitrix24_mcp/tools/daily_summary.py
fast_bitrix24_mcp/tools/deal.py
fast_bitrix24_mcp/tools/helper.py
fast_bitrix24_mcp/tools/inactive_clients.py
fast_bitrix24_mcp/tools/lead.py
fast_bitrix24_mcp/tools/main.py
fast_bitrix24_mcp/tools/manager_support.py
fast_bitrix24_mcp/tools/overdue_tasks.py
fast_bitrix24_mcp/tools/sales_funnel.py
fast_bitrix24_mcp/tools/task.py
fast_bitrix24_mcp/tools/top_clients.py
fast_bitrix24_mcp/tools/user.py
fast_bitrix24_mcp/tools/userfields.py
fast_bitrix24_mcp-1.0.15.dist-info/METADATA
fast_bitrix24_mcp-1.0.15.dist-info/WHEEL
fast_bitrix24_mcp-1.0.15.dist-info/top_level.txt
fast_bitrix24_mcp-1.0.15.dist-info/RECORD
