Metadata-Version: 2.4
Name: fast-bitrix24-mcp
Version: 1.0.15
Summary: MCP сервер для взаимодействия с Bitrix24 rest api на основе fast-bitrix24
Project-URL: Homepage, https://github.com/darkClaw921/fast-bitrix24-mcp
Project-URL: Documentation, https://github.com/darkClaw921/fast-bitrix24-mcp
Project-URL: Repository, https://github.com/darkClaw921/fast-bitrix24-mcp.git
Project-URL: Bug Tracker, https://github.com/darkClaw921/fast-bitrix24-mcp/issues
Project-URL: Changelog, https://github.com/darkClaw921/fast-bitrix24-mcp/blob/master/CHANGELOG.md
Requires-Python: >=3.12
Requires-Dist: fastmcp>=2.12.0
Requires-Dist: langchain-mcp-adapters>=0.1.7
Requires-Dist: langchain[openai]>=0.3.25
Requires-Dist: langgraph>=0.4.8
Requires-Dist: loguru>=0.7.3
Requires-Dist: orm-bitrix24>=0.1.4
Requires-Dist: python-dotenv>=1.1.0
Requires-Dist: pytz>=2025.2
Requires-Dist: fastapi>=0.115.0
Requires-Dist: uvicorn>=0.30.0
